{"areas":[],"images":[{"publication_date":"2016-03-01","media_name":"El País","media_country":"Spain","image_size":"750x1072","source_url":"http://img.kiosko.net/2016/03/01/es/elpais.750.jpg","missing":false},{"publication_date":"2016-03-02","media_name":"El País","media_country":"Spain","image_size":"750x1072","source_url":"http://img.kiosko.net/2016/03/02/es/elpais.750.jpg","missing":false},{"publication_date":"2016-03-03","media_name":"El País","media_country":"Spain","image_size":"750x1110","source_url":"http://img.kiosko.net/2016/03/03/es/elpais.750.jpg","missing":false},{"publication_date":"2016-03-04","media_name":"El País","media_country":"Spain","image_size":"750x1110","source_url":"http://img.kiosko.net/2016/03/04/es/elpais.750.jpg","missing":false},{"publication_date":"2016-03-05","media_name":"El País","media_country":"Spain","image_size":"750x1110","source_url":"http://img.kiosko.net/2016/03/05/es/elpais.750.jpg","missing":false},{"publication_date":"2016-03-06","media_name":"El País","media_country":"Spain","image_size":"750x1072","source_url":"http://img.kiosko.net/2016/03/06/es/elpais.750.jpg","missing":false},{"publication_date":"2016-03-07","media_name":"El País","media_country":"Spain","image_size":"750x1072","source_url":"http://img.kiosko.net/2016/03/07/es/elpais.750.jpg","missing":false},{"publication_date":"2016-03-08","media_name":"El País","media_country":"Spain","image_size":"750x1072","source_url":"http://img.kiosko.net/2016/03/08/es/elpais.750.jpg","missing":false},{"publication_date":"2016-03-09","media_name":"El País","media_country":"Spain","image_size":"750x1072","source_url":"http://img.kiosko.net/2016/03/09/es/elpais.750.jpg","missing":false},{"publication_date":"2016-03-10","media_name":"El País","media_country":"Spain","image_size":"750x1072","source_url":"http://img.kiosko.net/2016/03/10/es/elpais.750.jpg","missing":false},{"publication_date":"2016-03-11","media_name":"El País","media_country":"Spain","image_size":"750x1072","source_url":"http://img.kiosko.net/2016/03/11/es/elpais.750.jpg","missing":false},{"publication_date":"2016-03-12","media_name":"El País","media_country":"Spain","image_size":"750x1110","source_url":"http://img.kiosko.net/2016/03/12/es/elpais.750.jpg","missing":false},{"publication_date":"2016-03-13","media_name":"El País","media_country":"Spain","image_size":"750x1072","source_url":"http://img.kiosko.net/2016/03/13/es/elpais.750.jpg","missing":false},{"publication_date":"2016-03-14","media_name":"El País","media_country":"Spain","image_size":"750x1072","source_url":"http://img.kiosko.net/2016/03/14/es/elpais.750.jpg","missing":false},{"publication_date":"2016-03-15","media_name":"El País","media_country":"Spain","image_size":"750x1072","source_url":"http://img.kiosko.net/2016/03/15/es/elpais.750.jpg","missing":false},{"publication_date":"2016-03-16","media_name":"El País","media_country":"Spain","image_size":"750x1072","source_url":"http://img.kiosko.net/2016/03/16/es/elpais.750.jpg","missing":false},{"publication_date":"2016-03-17","media_name":"El País","media_country":"Spain","image_size":"750x1072","source_url":"http://img.kiosko.net/2016/03/17/es/elpais.750.jpg","missing":false},{"publication_date":"2016-03-18","media_name":"El País","media_country":"Spain","image_size":"750x1072","source_url":"http://img.kiosko.net/2016/03/18/es/elpais.750.jpg","missing":false},{"publication_date":"2016-03-19","media_name":"El País","media_country":"Spain","image_size":"750x1110","source_url":"http://img.kiosko.net/2016/03/19/es/elpais.750.jpg","missing":false},{"publication_date":"2016-03-20","media_name":"El País","media_country":"Spain","image_size":"750x1072","source_url":"http://img.kiosko.net/2016/03/20/es/elpais.750.jpg","missing":false},{"publication_date":"2016-03-21","media_name":"El País","media_country":"Spain","image_size":"750x1072","source_url":"http://img.kiosko.net/2016/03/21/es/elpais.750.jpg","missing":false},{"publication_date":"2016-03-22","media_name":"El País","media_country":"Spain","image_size":"750x1072","source_url":"http://img.kiosko.net/2016/03/22/es/elpais.750.jpg","missing":false},{"publication_date":"2016-03-23","media_name":"El País","media_country":"Spain","image_size":"750x1072","source_url":"http://img.kiosko.net/2016/03/23/es/elpais.750.jpg","missing":false},{"publication_date":"2016-03-24","media_name":"El País","media_country":"Spain","image_size":"750x1072","source_url":"http://img.kiosko.net/2016/03/24/es/elpais.750.jpg","missing":false},{"publication_date":"2016-03-25","media_name":"El País","media_country":"Spain","image_size":"750x1072","source_url":"http://img.kiosko.net/2016/03/25/es/elpais.750.jpg","missing":false},{"publication_date":"2016-03-26","media_name":"El País","media_country":"Spain","image_size":"750x1072","source_url":"http://img.kiosko.net/2016/03/26/es/elpais.750.jpg","missing":false},{"publication_date":"2016-03-27","media_name":"El País","media_country":"Spain","image_size":"750x1072","source_url":"http://img.kiosko.net/2016/03/27/es/elpais.750.jpg","missing":false},{"publication_date":"2016-03-28","media_name":"El País","media_country":"Spain","image_size":"750x1072","source_url":"http://img.kiosko.net/2016/03/28/es/elpais.750.jpg","missing":false},{"publication_date":"2016-03-29","media_name":"El País","media_country":"Spain","image_size":"750x1072","source_url":"http://img.kiosko.net/2016/03/29/es/elpais.750.jpg","missing":false},{"publication_date":"2016-03-30","media_name":"El País","media_country":"Spain","image_size":"750x1072","source_url":"http://img.kiosko.net/2016/03/30/es/elpais.750.jpg","missing":false},{"publication_date":"2016-03-31","media_name":"El País","media_country":"Spain","image_size":"750x1072","source_url":"http://img.kiosko.net/2016/03/31/es/elpais.750.jpg","missing":false}]}